sjd/__init__.py
sjd/py.typed
sjd/_/__init__.py
sjd/_/_type_alias.py
sjd/database/__init__.py
sjd/database/_collection.py
sjd/database/_configuration.py
sjd/database/_descriptors.py
sjd/database/_engine.py
sjd/database/_entity_tracker.py
sjd/entity/__init__.py
sjd/entity/_adv_property.py
sjd/entity/_entity.py
sjd/entity/_master_entity.py
sjd/entity/_property.py
sjd/entity/_property_options.py
sjd/entity/properties/__init__.py
sjd/entity/properties/_bool_property.py
sjd/entity/properties/_complex_property.py
sjd/entity/properties/_datetime_property.py
sjd/entity/properties/_float_property.py
sjd/entity/properties/_int_property.py
sjd/entity/properties/_list_property.py
sjd/entity/properties/_optional_property.py
sjd/entity/properties/_property_grabber.py
sjd/entity/properties/_str_property.py
sjd/query/__init__.py
sjd/query/_abstract_builders.py
sjd/query/_combined_query_builder.py
sjd/query/_query.py
sjd/query/_query_builder.py
sjd/query/_query_factory.py
sjd/query/_queryable.py
sjd/serialization/__init__.py
sjd/serialization/_deserializer.py
sjd/serialization/_serializable.py
sjd/serialization/_serializer.py
sjd/serialization/_shared.py
json_entity-0.1.3.1.dist-info/LICENSE
json_entity-0.1.3.1.dist-info/METADATA
json_entity-0.1.3.1.dist-info/WHEEL
json_entity-0.1.3.1.dist-info/top_level.txt
json_entity-0.1.3.1.dist-info/RECORD
