Metadata-Version: 2.1
Name: json-entity
Version: 0.1.3.1
Summary: A simple and async json database.
Home-page: https://github.com/immmdreza/simple-json-db
Author: immmdreza
Author-email: ir310022@gmail.com
Project-URL: Bug Tracker, https://github.com/immmdreza/simple-json-db/issues
Classifier: Programming Language :: Python :: 3
Classifier: License :: OSI Approved :: MIT License
Classifier: Operating System :: OS Independent
Requires-Python: >=3.10
License-File: LICENSE
Requires-Dist: aiofiles
Requires-Dist: ijson
